publisher/__init__.py
publisher/api.py
publisher/classes.py
publisher/cli.py
publisher/exceptions.py
publisher/procedure_content.py
publisher/settings.py
publisher/touchsurgery.py
publisher/utils.py
publisher/validators.py
publisher/git_handling/__init__.py
publisher/git_handling/history.py
publisher/git_handling/notes.py
publisher/git_handling/setup.py
publisher/gui/__init__.py
publisher/gui/channel_editor.py
publisher/gui/delegates.py
publisher/gui/models.py
publisher/gui/widgets.py
publisher/gui/ui/__init__.py
publisher/gui/ui/channel_editor.py
publisher/gui/ui/icons_rc.py
publisher/gui/ui/ts_title.py
publisher/processing/__init__.py
publisher/processing/models.py
publisher/processing/procedure.py
publisher/processing/data_sources/__init__.py
publisher/processing/data_sources/asset.py
publisher/processing/data_sources/author.py
publisher/processing/data_sources/csv_steps_file.py
publisher/processing/data_sources/eula.py
publisher/processing/data_sources/ftrack.py
publisher/processing/data_sources/info_card.py
publisher/processing/data_sources/organisation.py
publisher/processing/data_sources/overview.py
publisher/processing/data_sources/production_csv.py
publisher/processing/data_sources/step.py
publisher/processing/data_sources/thumbnail.py
publisher/processing/data_sources/utils.py
publisher/processing/utils/__init__.py
publisher/processing/utils/file.py
publisher/studio-report/.npmignore
publisher/studio-report/.prettierignore
publisher/studio-report/README.md
publisher/studio-report/generateLocalDocs.js
publisher/studio-report/package.json
publisher/studio-report/src/components.js
publisher/studio-report/src/const.js
publisher/studio-report/src/main.js
publisher/studio-report/src/payloadGenerator.js
publisher/studio-report/src/assets/missing_file_base64.txt
publisher/studio-report/src/utilities/image.js
publisher/studio-report/src/utilities/io.js
publisher/studio-report/src/utilities/translations.js
publisher/studio-report/src/utilities/video.js
tspublisher-0.0.1.dev3320.dist-info/METADATA
tspublisher-0.0.1.dev3320.dist-info/WHEEL
tspublisher-0.0.1.dev3320.dist-info/entry_points.txt
tspublisher-0.0.1.dev3320.dist-info/top_level.txt
tspublisher-0.0.1.dev3320.dist-info/RECORD
