Metadata-Version: 2.1
Name: tspublisher
Version: 0.0.1.dev3320
Summary: Touch Surgery publishing tools
Home-page: https://www.touchsurgery.com/jobs
Author: TS Content Squad
Author-email: admin@touchsurgery.com
License: GNU General Public License
Platform: UNKNOWN
Requires-Dist: requests
Requires-Dist: ruamel.yaml
Requires-Dist: gitpython
Requires-Dist: pycryptodome
Requires-Dist: yolk
Requires-Dist: pillow
Requires-Dist: future
Requires-Dist: polib
Requires-Dist: six
Requires-Dist: ftrack-python-api
Requires-Dist: yamale (==2.2.0)
Requires-Dist: fasteners
Provides-Extra: development
Requires-Dist: codecov ; extra == 'development'
Requires-Dist: flake8 ; extra == 'development'
Requires-Dist: mock ; extra == 'development'
Requires-Dist: pytest ; extra == 'development'
Requires-Dist: pytest-cov ; extra == 'development'
Requires-Dist: pytest-pep8 ; extra == 'development'
